COPYING.txt
HISTORY.txt
MANIFEST.in
README.rst
manual_test.py
setup.cfg
setup.py
pdbi/__init__.py
pdbi/__main__.py
pdbi.egg-info/PKG-INFO
pdbi.egg-info/SOURCES.txt
pdbi.egg-info/dependency_links.txt
pdbi.egg-info/entry_points.txt
pdbi.egg-info/requires.txt
pdbi.egg-info/top_level.txt
pdbi.egg-info/zip-safe
tests/__init__.py
tests/test_import.py