Metadata-Version: 1.1
Name: pdbi
Version: 0.1
Summary: Improved IPython-enabled pdb
Home-page: https://github.com/amitassaraf/pdbi
Author: Amit Assaraf
Author-email: amit@helpi.me
License: GPL
Keywords: pdb ipython pdbi
Platform: UNKNOWN
Classifier: Programming Language :: Python :: 2.5
Classifier: Programming Language :: Python :: 2.6
Classifier: Programming Language :: Python :: 2.7
Classifier: Programming Language :: Python :: 3
Classifier: Programming Language :: Python :: 3.2
Classifier: Operating System :: MacOS :: MacOS X
Classifier: Operating System :: POSIX :: Linux
Classifier: Operating System :: Microsoft :: Windows
Classifier: Topic :: Software Development :: Debuggers
